app_global/config.py
app_global-1.0.0.dist-info/LICENSE
app_global-1.0.0.dist-info/WHEEL
app_global-1.0.0.dist-info/METADATA
app_global-1.0.0.dist-info/RECORD
